pystk2.cp312-win_amd64.pyd
pysupertuxkart2-0.6.8.dist-info/METADATA
pysupertuxkart2-0.6.8.dist-info/WHEEL
pysupertuxkart2-0.6.8.dist-info/licenses/COPYING
pysupertuxkart2-0.6.8.dist-info/RECORD
