Metadata-Version: 2.2
Name: PySuperTuxKart2
Version: 0.6.8
Summary: Python bindings for SuperTuxKart
Author-Email: Benjamin Piwowarski <benjamin@piwowarski.fr>
Classifier: Development Status :: 4 - Beta
Classifier: License :: OSI Approved :: MIT License
Classifier: Programming Language :: Python :: 3 :: Only
Classifier: Programming Language :: Python :: 3.8
Classifier: Programming Language :: Python :: 3.9
Classifier: Programming Language :: Python :: 3.10
Classifier: Programming Language :: Python :: 3.11
Project-URL: repository, https://github.com/bpiwowar/pystk2
Project-URL: documentation, https://pystk2.readthedocs.io/
Requires-Python: >=3.8
Requires-Dist: numpy
Requires-Dist: platformdirs
Requires-Dist: requests
